[
    {
        "id":1,
        "name":"tanver",
        "gender":"male",
        "contact":"0987635",
        "address":"nuyakandha,jajira,dhaka",
        "photo_url":"image/google"
    },
    {
        "id":2,
        "name":"sakib",
        "gender":"male",
        "contact":"098700",
        "address":"nuyakandha,jajira,dhaka",
        "photo_url":"image/google"
    },
    {
        "id":3,
        "name":"asif",
        "gender":"male",
        "contact":"09899005",
        "address":"nuyakandha,jajira,dhaka",
        "photo_url":"image/google"
    }
]